{
	"description": "",
	"displayName": "InputAction",
	"methods": [
		{
			"name": "getValue",
			"docblock": null,
			"modifiers": [],
			"params": [],
			"returns": null
		},
		{
			"name": "setValue",
			"docblock": null,
			"modifiers": [],
			"params": [
				{
					"name": "value",
					"type": null
				}
			],
			"returns": null
		},
		{
			"name": "resetValue",
			"docblock": null,
			"modifiers": [],
			"params": [],
			"returns": null
		},
		{
			"name": "setDisable",
			"docblock": null,
			"modifiers": [],
			"params": [
				{
					"name": "value",
					"type": null
				}
			],
			"returns": null
		},
		{
			"name": "onChange",
			"docblock": null,
			"modifiers": [],
			"params": [
				{
					"name": "e",
					"type": null
				},
				{
					"name": "v",
					"type": null
				}
			],
			"returns": null
		},
		{
			"name": "onBlur",
			"docblock": null,
			"modifiers": [],
			"params": [
				{
					"name": "e",
					"type": null
				}
			],
			"returns": null
		},
		{
			"name": "setFloatingLabelStyle",
			"docblock": null,
			"modifiers": [],
			"params": [
				{
					"name": "rightIconList",
					"type": null
				},
				{
					"name": "leftIconList",
					"type": null
				}
			],
			"returns": null
		},
		{
			"name": "getFloatingLabelStyle",
			"docblock": null,
			"modifiers": [],
			"params": [
				{
					"name": "usePropValue",
					"type": null
				},
				{
					"name": "rightIconList",
					"type": null
				},
				{
					"name": "leftIconList",
					"type": null
				}
			],
			"returns": null
		},
		{
			"name": "passwordClicked",
			"docblock": null,
			"modifiers": [],
			"params": [],
			"returns": null
		},
		{
			"name": "focus",
			"docblock": null,
			"modifiers": [],
			"params": [],
			"returns": null
		},
		{
			"name": "hideLeftIcons",
			"docblock": null,
			"modifiers": [],
			"params": [],
			"returns": null
		},
		{
			"name": "hideRightIcons",
			"docblock": null,
			"modifiers": [],
			"params": [],
			"returns": null
		},
		{
			"name": "showLeftIcons",
			"docblock": null,
			"modifiers": [],
			"params": [],
			"returns": null
		},
		{
			"name": "showRightIcons",
			"docblock": null,
			"modifiers": [],
			"params": [],
			"returns": null
		},
		{
			"name": "validateConstraint",
			"docblock": null,
			"modifiers": [],
			"params": [],
			"returns": null
		},
		{
			"name": "renderBInput",
			"docblock": null,
			"modifiers": [],
			"params": [
				{
					"name": "type",
					"type": null
				},
				{
					"name": "leftIcons",
					"type": null
				},
				{
					"name": "rightIcons",
					"type": null
				}
			],
			"returns": null
		},
		{
			"name": "renderBInputNumeric",
			"docblock": null,
			"modifiers": [],
			"params": [
				{
					"name": "leftIcons",
					"type": null
				},
				{
					"name": "rightIcons",
					"type": null
				}
			],
			"returns": null
		}
	],
	"props": {
		"canActionFocusable": {
			"type": {
				"name": "bool"
			},
			"required": false,
			"description": "If `true`, icons will be focussable.",
			"defaultValue": {
				"value": false,
				"computed": false
			}
		},
		"hideLeftIcons": {
			"type": {
				"name": "bool"
			},
			"required": false,
			"description": "If `true`, all left icons will be hidden.",
			"defaultValue": {
				"value": false,
				"computed": false
			}
		},
		"hideRightIconKeyList": {
			"type": {
				"name": "arrayOf",
				"value": {
					"name": "custom",
					"raw": "String"
				}
			},
			"required": false,
			"description": "If `true`, selected icons will be hidden."
		},
		"hideRightIcons": {
			"type": {
				"name": "bool"
			},
			"required": false,
			"description": "If `true`, all right icons will be hidden.",
			"defaultValue": {
				"value": false,
				"computed": false
			}
		},
		"inputDisabled": {
			"type": {
				"name": "bool"
			},
			"required": false,
			"description": "If `true`, only the input element will be disabled.",
			"defaultValue": {
				"value": false,
				"computed": false
			}
		},
		"leftIconList": {
			"type": {
				"name": "array"
			},
			"required": false,
			"description": "icons will be showed in left side of input elements."
		},
		"rightIconList": {
			"type": {
				"name": "array"
			},
			"required": false,
			"description": "icons will be showed in right side of input elements."
		},
		"type": {
			"defaultValue": {
				"value": "text",
				"computed": false
			},
			"required": false
		}
	},
	"composes": [
		"@boa/base",
		"@boa/components/Input"
	]
}