[
   {
      "variantName":"default",
      "type":"BAgrementViewer",
      "props":{          
           
         "resourceInfo":{
            "id":932,
            "name":"Önizleme",
            "iconPath":"window_hide_99ts.png",
            "sortId":9999,
            "isHidden":true,
            "isLeaf":true,
            "description":"Önizleme",
            "toolTipImagePath":"",
            
            "channelId":0,
            "uiType":0,
            
            "resourceActionList":[
               {
                  "resourceId":932,
                  "actionId":13,
                  "actionType":0,
                  "name":"YAZDIR",
                  "commandName":"Ok",
                  "groupName":"",
                  "description":"Tamam",
                  "iconPath":"SettingsBackupRestore",
                  "isVirtual":false,
                  "isAssignable":true,
                  "hasAccounting":false,
                  "hasSlip":false,
                  "hasCommission":false,
                  "hasWorkflow":false,
                  "sortId":1,
                  "userName":null,
                  "systemDate":"0001-01-01T00:00:00",
                  "hostName":null,
                  "updateUserName":null,
                  "updateSystemDate":null,
                  "updateHostName":null,
                  "hostIP":null,
                  "hasAuthorization":false,
                  "hasTellerTransaction":false,
                  "hasRevokableTransaction":false,
                  "hasFutureDated":false,
                  "isSelected":false,
                  "isSelectable":true
               },
               {
                  "resourceId":932,
                  "actionId":14,
                  "actionType":0,
                  "name":"INDIR",
                  "commandName":"Ok",
                  "groupName":"",
                  "description":"Tamam",
                  "iconPath":"SettingsBackupRestore",
                  "isVirtual":false,
                  "isAssignable":true,
                  "hasAccounting":false,
                  "hasSlip":false,
                  "hasCommission":false,
                  "hasWorkflow":false,
                  "sortId":2,
                  "userName":null,
                  "systemDate":"0001-01-01T00:00:00",
                  "hostName":null,
                  "updateUserName":null,
                  "updateSystemDate":null,
                  "updateHostName":null,
                  "hostIP":null,
                  "hasAuthorization":false,
                  "hasTellerTransaction":false,
                  "hasRevokableTransaction":false,
                  "hasFutureDated":false,
                  "isSelected":false,
                  "isSelectable":true
               }

            ],
            "openState":0,
            "openedBy":0,
            "isWorkflow":false,
            "isRevokable":false,
            "workflowData":null,
            "resourceCode":"IBLTAKACRS",
            "lastAccessTime":null,
            "ribbonToolSizingMode":0,
            "helpURL":"https://bilge/boa-yardim/is-akisi/is-akisi-takip/1678-shorttitle-7-1599",
            "searchTag":"",
            "moduleCode":"Yönetsel İşlemler",
            "userName":"demirci",
            "updateUserName":"suatc",
            "businessOwnerWorkgroupName":null,
            "systemDate":"2012-05-18T10:42:47.247",
            "updateSystemDate":null,
            "fullPath":"Ekran Listesi > Ana Menü > İş Akışı > İş Akışı Menü > İş Akışı Takip > Aksiyon Gerekçeleri",
            "isPersonalResource":false,
            "isNew":false,
            "clickedMenu":null,
            "typeId":0,
            "isActive":false,
            "children":[

            ],
            "parent":null,
            "identity":932,
            "isExpanded":false,
            "isSelected":false,
            "isSelectable":true,
            "isChecked":false,
            "isCheckBoxVisible":false
         }
      }
   }
]